[{"pregunta":"\u00bfQue animal da nombre a las Islas Canarias?","rta1":"Canario","rta2":"Ave","rtaC":"Perro"},{"pregunta":"Si en una pecera hay 12 peces y 5 de ellos se ahogan, cuantos peces quedan?","rta1":"7","rta2":"5","rtaC":"12"},{"pregunta":"\u00bfDe que color son las cajas negras de los aviones?","rta1":"Negra","rta2":"Blanca","rtaC":"Naranja"},{"pregunta":"Est\u00e1s corriendo en una carrera y adelantas a la persona que esta en segundo lugar, en que posicion pasas a estar?","rta1":"Primero","rta2":"Tercero","rtaC":"Segundo"},{"pregunta":"\u00bfCuanto duro la Guerra de los 100 a\u00f1os?","rta1":"100","rta2":"101","rtaC":"116"}]